SunSynk_j0nnyboi/SunSynk.py
SunSynk_j0nnyboi/__init__.py
SunSynk_j0nnyboi/examples.py
SunSynk_j0nnyboi-0.0.2.dist-info/METADATA
SunSynk_j0nnyboi-0.0.2.dist-info/WHEEL
SunSynk_j0nnyboi-0.0.2.dist-info/top_level.txt
SunSynk_j0nnyboi-0.0.2.dist-info/RECORD
